Workbook

Sheet Income Statement
B2: Income Statement
C3: Year 1 | D3: Year 2 | E3: Year 3 | F3: Year 4
B4: Revenue | C4: 60000 | D4: =7000*12 -> 84000 | E4: 180000 | F4: =E4*1.25 -> 225000
B5: Cost of Goods Sold (COGS) | C5: 12000 | D5: =2000*12 -> 24000 | E5: 60000 | F5: =F4*0.15 -> 33750
B6: Gross Profit | C6: =C4-C5 -> 48000 | D6: =D4-D5 -> 60000 | E6: =E4-E5 -> 120000 | F6: =F4-F5 -> 191250
B7: Selling and Administrative Expenses
B8: Salary | C8: 36000 | D8: =C8 -> 36000 | E8: 72000 | F8: =36000*3 -> 108000
B9: Depreciation | C9: 1000 | D9: =1000+300 -> 1300 | E9: 2600 | F9: =2600 -> 2600
B10: Car Rental | F10: 2000
B11: Total S&A Expenses | C11: =SUM(C8:C9) -> 37000 | D11: =D8+D9 -> 37300 | E11: =E8+E9 -> 74600 | F11: =F8+F9+F10 -> 112600
B12: Operating Income | C12: =C6-C11 -> 11000 | D12: =D6-D11 -> 22700 | E12: =E6-E11 -> 45400 | F12: =F6-F11 -> 78650
B13: Interest expense | C13: 500 | D13: 500 | E13: 500 | F13: 500
B14: Income before taxes | C14: =C12-C13 -> 10500 | D14: =D12-D13 -> 22200 | E14: =E12-E13 -> 44900 | F14: =F12-F13 -> 78150
B15: Tax expense | C15: =C14*0.1 -> 1050 | D15: =D14*0.1 -> 2220 | E15: =E14*0.1 -> 4490 | F15: =F14*0.1 -> 7815
B16: Net Income | C16: =C14-C15 -> 9450 | D16: =D14-D15 -> 19980 | E16: =E14-E15 -> 40410 | F16: =F14-F15 -> 70335

Sheet Balance Sheet
B2: Balance Sheet
C4: Year 1 | D4: Year 2 | E4: Year 3 | F4: Year 4 | H4: Year 1 | I4: Year 2 | J4: Year 3 | K4: Year 4
B5: Assets | G5: Liabilities
B6: Current Assets
B7: Cash | C7: =9450+1000 -> 10450 | D7: =C7-3000+19980+1300 -> 28730 | E7: =D7+'Income Statement'!E16+'Income Statement'!E9-13000-10000 -> 48740 | F7: =E7+'Income Statement'!F16+'Income Statement'!F9-5000+10000-15000-F8 -> 111242.31 | G7: Bank Loan | H7: 5000 | I7: =H7 -> 5000 | J7: 5000 | K7: 0
B8: A/R | F8: =0.1*'Income Statement'!F4*(1/52) -> 432.69231
B10: Fixed Assets
B11: Car | C11: 10000 | D11: 10000 | E11: 20000 | F11: 20000
B12: Accum. Depreciation | C12: -1000 | D12: -2000 | E12: -4000 | F12: -6000
B13: Car (net) | C13: =C11+C12 -> 9000 | D13: =D11+D12 -> 8000 | E13: =E11+E12 -> 16000 | F13: =F11+F12 -> 14000 | G13: Equity
B14: LCD TV | D14: 3000 | E14: 6000 | F14: 6000 | G14: Contributed Capital | H14: 5000 | I14: 5000 | J14: 5000 | K14: =5000+10000 -> 15000
B15: Accum. Depreciation | D15: -300 | E15: -900 | F15: -1500 | G15: Retained Earnings | H15: ='Income Statement'!C16 -> 9450 | I15: =H15+'Income Statement'!D16 -> 29430 | J15: =I15+'Income Statement'!E16-10000 -> 59840 | K15: =J15+'Income Statement'!F16-15000 -> 115175
B16: LCD (net) | D16: =D14+D15 -> 2700 | E16: =E14+E15 -> 5100 | F16: =F14+F15 -> 4500
B19: Total Assets | C19: =C7+C13 -> 19450 | D19: =D7+D13+D16 -> 39430 | E19: =E7+E13+E16 -> 69840 | F19: =F7+F8+F13+F16 -> 130175 | G19: Total Liabilities and Equity | H19: =H7+H14+H15 -> 19450 | I19: =I7+I14+I15 -> 39430 | J19: =J7+J14+J15 -> 69840 | K19: =K7+K14+K15 -> 130175

Sheet Cash Flow Statements
B1: Cash Flow Statement
C2: Year 1 | D2: Year 2 | E2: Year 3 | F2: Year 4
B3: Operating Activities
B4: Net Income | C4: ='Income Statement'!C16 -> 9450 | D4: ='Income Statement'!D16 -> 19980 | E4: ='Income Statement'!E16 -> 40410 | F4: ='Income Statement'!F16 -> 70335
B5: Depreciation (+) | C5: 1000 | D5: 1300 | E5: ='Income Statement'!E9 -> 2600 | F5: 2600
B6: Changes in working capital
B7: Increase in Account receviable (-) | F7: -433
B8: Increase in Account payable (+)
B10: Cash provided by operating activities | C10: =C4+C5 -> 10450 | D10: =D4+D5 -> 21280 | E10: =SUM(E4:E8) -> 43010 | F10: =SUM(F4:F8) -> 72502
B12: Invesing Activities
B13: Capital Expenditure (-) | C13: -10000 | D13: -3000 | E13: -13000
B14: Sale of long-term asset (+)
B16: Cash provided by investing activities | C16: =C13 -> -10000 | D16: =D13 -> -3000 | E16: =SUM(E13:E14) -> -13000 | F16: =SUM(F13:F14) -> 0
B18: Financing Activities
B19: Issurance of Bond/Loan (+) | C19: 5000 | D19: 0 | E19: 0 | F19: 0
B20: Issurance of Common Stocks (+) | C20: 5000 | D20: 0 | E20: 0 | F20: 10000
B21: Repayment of long-term debt (-) | E21: 0 | F21: -5000
B22: Dividends paid (-) | E22: -10000 | F22: -15000
B24: Cash provided by financing activities | C24: =C19+C20 -> 10000 | D24: 0 | E24: =SUM(E19:E22) -> -10000 | F24: =SUM(F19:F22) -> -10000
B26: Increase (Decrease) in Cash | C26: =C10+C16+C24 -> 10450 | D26: =D10+D16+D24 -> 18280 | E26: =E10+E16+E24 -> 20010 | F26: =F10+F16+F24 -> 62502
